[
  { "type": "assisted" },
  { "type": "band" },
  { "type": "barbell" },
  { "type": "body weight" },
  { "type": "bosu ball" },
  { "type": "cable" },
  { "type": "dumbbell" },
  { "type": "elliptical machine" },
  { "type": "ez barbell" },
  { "type": "hammer" },
  { "type": "kettlebell" },
  { "type": "leverage machine" },
  { "type": "medicine ball" },
  { "type": "olympic barbell" },
  { "type": "resistance band" },
  { "type": "roller" },
  { "type": "rope" },
  { "type": "skierg machine" },
  { "type": "sled machine" },
  { "type": "smith machine" },
  { "type": "stability ball" },
  { "type": "stationary bike" },
  { "type": "stepmill machine" },
  { "type": "tire" },
  { "type": "trap bar" },
  { "type": "upper body ergometer" },
  { "type": "weighted" },
  { "type": "wheel roller" }
]